threadsafe_datastore/__init__.py
threadsafe_datastore/store.py
threadsafe_datastore/utils.py
threadsafe_datastore-1.0.0.dist-info/licenses/LICENSE
threadsafe_datastore-1.0.0.dist-info/METADATA
threadsafe_datastore-1.0.0.dist-info/WHEEL
threadsafe_datastore-1.0.0.dist-info/top_level.txt
threadsafe_datastore-1.0.0.dist-info/RECORD
