Metadata-Version: 2.4
Name: threadsafe-datastore
Version: 1.0.0
Summary: A thread-safe key-value data store with atomic operations and nested access
Author-email: Keith <keith@hlfshell.ai>
License: MIT
Project-URL: Homepage, https://github.com/hlfshell/threadsafe-datastore
Project-URL: Repository, https://github.com/hlfshell/threadsafe-datastore
Project-URL: Issues, https://github.com/hlfshell/threadsafe-datastore/issues
Keywords: thread-safe,datastore,concurrent,atomic
Classifier: Development Status :: 4 - Beta
Classifier: Intended Audience :: Developers
Classifier: License :: OSI Approved :: MIT License
Classifier: Programming Language :: Python :: 3
Classifier: Programming Language :: Python :: 3.8
Classifier: Programming Language :: Python :: 3.9
Classifier: Programming Language :: Python :: 3.10
Classifier: Programming Language :: Python :: 3.11
Classifier: Programming Language :: Python :: 3.12
Classifier: Topic :: Software Development :: Libraries :: Python Modules
Requires-Python: >=3.8
License-File: LICENSE
Provides-Extra: dev
Requires-Dist: pytest>=7.0; extra == "dev"
Requires-Dist: pytest-cov>=4.0; extra == "dev"
Requires-Dist: mypy>=1.0; extra == "dev"
Requires-Dist: black>=23.0; extra == "dev"
Requires-Dist: ruff>=0.1.0; extra == "dev"
Dynamic: license-file
